import android.content.Context;

// 
// Decompiled by Procyon v0.6.0
// 

public final class ayh extends eus
{
    public ayh(final tcv p0, final mws p1, final hss p2, final gh7<bo6> p3, final gdf<cxs> p4, final brb p5, final tod p6, final epi<cxs> p7, final Context p8, final sc p9, final vxs p10, final w0t p11, final c3e<cxs> p12, final xba<bo> p13, final udx p14, final efv p15, final l6j<tmi, e2g<n3e<Object>>> p16) {
        // 
        // This method could not be decompiled.
        // 
        // Original Bytecode:
        // 
        //     1: aload_1        
        //     2: aload_2        
        //     3: aload_3        
        //     4: aload           4
        //     6: aload           5
        //     8: aload           6
        //    10: aload           7
        //    12: aload           8
        //    14: aload           10
        //    16: aload           11
        //    18: aload           12
        //    20: aload           13
        //    22: aload           14
        //    24: aload           15
        //    26: aload           16
        //    28: invokespecial   eus.<init>:(Ltcv;Lmws;Lhss;Lgh7;Lgdf;Lbrb;Ltod;Lepi;Lsc;Lvxs;Lw0t;Lc3e;Lxba;Ludx;Lefv;)V
        //    31: return         
        //    Signature:
        //  (Ltcv;Lmws;Lhss;Lgh7<Lbo6;>;Lgdf<Lcxs;>;Lbrb;Ltod;Lepi<Lcxs;>;Landroid/content/Context;Lsc;Lvxs;Lw0t;Lc3e<Lcxs;>;Lxba<Lbo;>;Ludx;Lefv;Ll6j<Ltmi;Le2g<Ln3e<Ljava/lang/Object;>;>;>;)V
        // 
        // The error that occurred was:
        // 
        // java.lang.ArrayIndexOutOfBoundsException: 17
        //     at com.strobel.decompiler.ast.AstBuilder.performStackAnalysis(AstBuilder.java:2030)
        //     at com.strobel.decompiler.ast.AstBuilder.build(AstBuilder.java:108)
        //     at com.strobel.decompiler.languages.java.ast.AstMethodBodyBuilder.createMethodBody(AstMethodBodyBuilder.java:203)
        //     at com.strobel.decompiler.languages.java.ast.AstMethodBodyBuilder.createMethodBody(AstMethodBodyBuilder.java:93)
        //     at com.strobel.decompiler.languages.java.ast.AstBuilder.createMethodBody(AstBuilder.java:868)
        //     at com.strobel.decompiler.languages.java.ast.AstBuilder.createConstructor(AstBuilder.java:799)
        //     at com.strobel.decompiler.languages.java.ast.AstBuilder.addTypeMembers(AstBuilder.java:635)
        //     at com.strobel.decompiler.languages.java.ast.AstBuilder.createTypeCore(AstBuilder.java:605)
        //     at com.strobel.decompiler.languages.java.ast.AstBuilder.createTypeNoCache(AstBuilder.java:195)
        //     at com.strobel.decompiler.languages.java.ast.AstBuilder.createType(AstBuilder.java:162)
        //     at com.strobel.decompiler.languages.java.ast.AstBuilder.addType(AstBuilder.java:137)
        //     at com.strobel.decompiler.languages.java.JavaLanguage.buildAst(JavaLanguage.java:71)
        //     at com.strobel.decompiler.languages.java.JavaLanguage.decompileType(JavaLanguage.java:59)
        //     at com.strobel.decompiler.DecompilerDriver.decompileType(DecompilerDriver.java:333)
        //     at com.strobel.decompiler.DecompilerDriver.decompileJar(DecompilerDriver.java:254)
        //     at com.strobel.decompiler.DecompilerDriver.main(DecompilerDriver.java:129)
        // 
        throw new IllegalStateException("An error occurred while decompiling this method.");
    }
    
    public final gdv$b l0(final gdv$b gdv$b) {
        gdv$b.a = "mutual_following";
        return gdv$b;
    }
    
    public final f4f n0() {
        return (f4f)new ve6((czr)new jmc((eus)this, 1), true, (ve6$a)this);
    }
}
