import com.twitter.util.user.UserIdentifier;
import android.view.LayoutInflater;
import android.content.res.Resources;
import android.content.Intent;

// 
// Decompiled by Procyon v0.6.0
// 

public final class flx extends vbv
{
    public flx(final glx p0, final int p1, final Intent p2, final r8x p3, final Resources p4, final kas p5, final pwe<bai> p6, final jn p7, final cnb p8, final faf p9, final hag p10, final LayoutInflater p11, final xba<q4h> p12, final UserIdentifier p13, final xbv p14, final pwe<qoa> p15, final f6g p16, final v8p p17, final vam p18, final obi<?> p19, final i7p p20, final t8p p21) {
        // 
        // This method could not be decompiled.
        // 
        // Original Bytecode:
        // 
        //     1: aload_2        
        //     2: aload_3        
        //     3: aload           4
        //     5: aload           5
        //     7: aload           6
        //     9: aload           7
        //    11: aload           8
        //    13: aload           9
        //    15: aload           10
        //    17: aload           11
        //    19: aload           12
        //    21: aload           13
        //    23: aload           14
        //    25: aload           15
        //    27: aload           16
        //    29: aload           17
        //    31: aload           18
        //    33: aload           19
        //    35: aload           20
        //    37: aload           21
        //    39: invokespecial   vbv.<init>:(Landroid/content/Intent;Lr8x;Landroid/content/res/Resources;Lkas;Lpwe;Ljn;Lcnb;Lfaf;Lhag;Landroid/view/LayoutInflater;Lxba;Lcom/twitter/util/user/UserIdentifier;Lxbv;Lpwe;Lf6g;Lv8p;Lvam;Lobi;Li7p;Lt8p;)V
        //    42: aload_0        
        //    43: aload_1        
        //    44: getfield        glx.t:Lxjx;
        //    47: ldc             2131624013
        //    49: aconst_null    
        //    50: aconst_null    
        //    51: bipush          6
        //    53: invokestatic    xjx.c:(Lxjx;ILandroid/view/ViewGroup;Lqsb;I)Lym6;
        //    56: checkcast       Lxjx$a;
        //    59: getfield        xjx$a.D0:Lpm6;
        //    62: invokeinterface pm6.getView:()Landroid/view/View;
        //    67: invokevirtual   u9.R4:(Landroid/view/View;)V
        //    70: return         
        //    Signature:
        //  (Lglx;ILandroid/content/Intent;Lr8x;Landroid/content/res/Resources;Lkas;Lpwe<Lbai;>;Ljn;Lcnb;Lfaf;Lhag;Landroid/view/LayoutInflater;Lxba<Lq4h;>;Lcom/twitter/util/user/UserIdentifier;Lxbv;Lpwe<Lqoa;>;Lf6g;Lv8p;Lvam;Lobi<*>;Li7p;Lt8p;)V
        // 
        // The error that occurred was:
        // 
        // java.lang.ArrayIndexOutOfBoundsException: 22
        //     at com.strobel.decompiler.ast.AstBuilder.performStackAnalysis(AstBuilder.java:2030)
        //     at com.strobel.decompiler.ast.AstBuilder.build(AstBuilder.java:108)
        //     at com.strobel.decompiler.languages.java.ast.AstMethodBodyBuilder.createMethodBody(AstMethodBodyBuilder.java:203)
        //     at com.strobel.decompiler.languages.java.ast.AstMethodBodyBuilder.createMethodBody(AstMethodBodyBuilder.java:93)
        //     at com.strobel.decompiler.languages.java.ast.AstBuilder.createMethodBody(AstBuilder.java:868)
        //     at com.strobel.decompiler.languages.java.ast.AstBuilder.createConstructor(AstBuilder.java:799)
        //     at com.strobel.decompiler.languages.java.ast.AstBuilder.addTypeMembers(AstBuilder.java:635)
        //     at com.strobel.decompiler.languages.java.ast.AstBuilder.createTypeCore(AstBuilder.java:605)
        //     at com.strobel.decompiler.languages.java.ast.AstBuilder.createTypeNoCache(AstBuilder.java:195)
        //     at com.strobel.decompiler.languages.java.ast.AstBuilder.createType(AstBuilder.java:162)
        //     at com.strobel.decompiler.languages.java.ast.AstBuilder.addType(AstBuilder.java:137)
        //     at com.strobel.decompiler.languages.java.JavaLanguage.buildAst(JavaLanguage.java:71)
        //     at com.strobel.decompiler.languages.java.JavaLanguage.decompileType(JavaLanguage.java:59)
        //     at com.strobel.decompiler.DecompilerDriver.decompileType(DecompilerDriver.java:333)
        //     at com.strobel.decompiler.DecompilerDriver.decompileJar(DecompilerDriver.java:254)
        //     at com.strobel.decompiler.DecompilerDriver.main(DecompilerDriver.java:129)
        // 
        throw new IllegalStateException("An error occurred while decompiling this method.");
    }
}
