import android.util.SparseArray;

// 
// Decompiled by Procyon v0.6.0
// 

public final class kmb
{
    public final String a;
    public final String b;
    public final SparseArray<mmb> c;
    
    public kmb(final String p0, final String p1, final SparseArray<mmb> p2, final mmb p3) {
        // 
        // This method could not be decompiled.
        // 
        // Original Bytecode:
        // 
        //     1: invokespecial   java/lang/Object.<init>:()V
        //     4: aload_0        
        //     5: aload_1        
        //     6: putfield        kmb.a:Ljava/lang/String;
        //     9: aload_0        
        //    10: aload_2        
        //    11: putfield        kmb.b:Ljava/lang/String;
        //    14: aload_0        
        //    15: aload_3        
        //    16: putfield        kmb.c:Landroid/util/SparseArray;
        //    19: return         
        //    Signature:
        //  (Ljava/lang/String;Ljava/lang/String;Landroid/util/SparseArray<Lmmb;>;Lmmb;)V
        // 
        // The error that occurred was:
        // 
        // java.lang.ArrayIndexOutOfBoundsException: 4
        //     at com.strobel.decompiler.ast.AstBuilder.performStackAnalysis(AstBuilder.java:2030)
        //     at com.strobel.decompiler.ast.AstBuilder.build(AstBuilder.java:108)
        //     at com.strobel.decompiler.languages.java.ast.AstMethodBodyBuilder.createMethodBody(AstMethodBodyBuilder.java:203)
        //     at com.strobel.decompiler.languages.java.ast.AstMethodBodyBuilder.createMethodBody(AstMethodBodyBuilder.java:93)
        //     at com.strobel.decompiler.languages.java.ast.AstBuilder.createMethodBody(AstBuilder.java:868)
        //     at com.strobel.decompiler.languages.java.ast.AstBuilder.createConstructor(AstBuilder.java:799)
        //     at com.strobel.decompiler.languages.java.ast.AstBuilder.addTypeMembers(AstBuilder.java:635)
        //     at com.strobel.decompiler.languages.java.ast.AstBuilder.createTypeCore(AstBuilder.java:605)
        //     at com.strobel.decompiler.languages.java.ast.AstBuilder.createTypeNoCache(AstBuilder.java:195)
        //     at com.strobel.decompiler.languages.java.ast.AstBuilder.createType(AstBuilder.java:162)
        //     at com.strobel.decompiler.languages.java.ast.AstBuilder.addType(AstBuilder.java:137)
        //     at com.strobel.decompiler.languages.java.JavaLanguage.buildAst(JavaLanguage.java:71)
        //     at com.strobel.decompiler.languages.java.JavaLanguage.decompileType(JavaLanguage.java:59)
        //     at com.strobel.decompiler.DecompilerDriver.decompileType(DecompilerDriver.java:333)
        //     at com.strobel.decompiler.DecompilerDriver.decompileJar(DecompilerDriver.java:254)
        //     at com.strobel.decompiler.DecompilerDriver.main(DecompilerDriver.java:129)
        // 
        throw new IllegalStateException("An error occurred while decompiling this method.");
    }
}
