// 
// Decompiled by Procyon v0.6.0
// 

public final class lk8 implements yes
{
    public final long a;
    public final long b;
    public final long c;
    public final long d;
    public final long e;
    public final long f;
    public final long g;
    public final long h;
    public final long i;
    public final long j;
    public final long k;
    public final long l;
    public final long m;
    public final long n;
    public final long o;
    public final long p;
    public final long q;
    public final long r;
    public final long s;
    public final long t;
    public final long u;
    
    public lk8(final long a, final long b, final long c, final long d, final long e, final long f, final long g, final long h, final long i, final long j, final long k, final long l, final long m, final long n, final long o, final long p21, final long q, final long r, final long s, final long t, final long u) {
        this.a = a;
        this.b = b;
        this.c = c;
        this.d = d;
        this.e = e;
        this.f = f;
        this.g = g;
        this.h = h;
        this.i = i;
        this.j = j;
        this.k = k;
        this.l = l;
        this.m = m;
        this.n = n;
        this.o = o;
        this.p = p21;
        this.q = q;
        this.r = r;
        this.s = s;
        this.t = t;
        this.u = u;
    }
    
    public final q7r<pr4> a(final boolean b, final boolean b2, final m76 m76, final int n) {
        m76.x(225259054);
        final ea6$b a = ea6.a;
        long n2;
        if (!b) {
            n2 = this.m;
        }
        else if (b2) {
            n2 = this.n;
        }
        else {
            n2 = this.l;
        }
        final q7r v = nkz.v((Object)new pr4(n2), m76);
        m76.O();
        return (q7r<pr4>)v;
    }
    
    public final q7r<pr4> b(final boolean p0, final m76 p1, final int p2) {
        // 
        // This method could not be decompiled.
        // 
        // Original Bytecode:
        // 
        //     1: ldc             -1423938813
        //     3: invokeinterface m76.x:(I)V
        //     8: getstatic       ea6.a:Lea6$b;
        //    11: astore_2       
        //    12: new             Lpr4;
        //    15: dup            
        //    16: aload_0        
        //    17: getfield        lk8.o:J
        //    20: invokespecial   pr4.<init>:(J)V
        //    23: aload_1        
        //    24: invokestatic    nkz.v:(Ljava/lang/Object;Lm76;)Lq7r;
        //    27: astore_2       
        //    28: aload_1        
        //    29: invokeinterface m76.O:()V
        //    34: aload_2        
        //    35: areturn        
        //    Signature:
        //  (ZLm76;I)Lq7r<Lpr4;>;
        // 
        // The error that occurred was:
        // 
        // java.lang.ArrayIndexOutOfBoundsException: 3
        //     at com.strobel.decompiler.ast.AstBuilder.performStackAnalysis(AstBuilder.java:2016)
        //     at com.strobel.decompiler.ast.AstBuilder.build(AstBuilder.java:108)
        //     at com.strobel.decompiler.languages.java.ast.AstMethodBodyBuilder.createMethodBody(AstMethodBodyBuilder.java:203)
        //     at com.strobel.decompiler.languages.java.ast.AstMethodBodyBuilder.createMethodBody(AstMethodBodyBuilder.java:93)
        //     at com.strobel.decompiler.languages.java.ast.AstBuilder.createMethodBody(AstBuilder.java:868)
        //     at com.strobel.decompiler.languages.java.ast.AstBuilder.createMethod(AstBuilder.java:761)
        //     at com.strobel.decompiler.languages.java.ast.AstBuilder.addTypeMembers(AstBuilder.java:638)
        //     at com.strobel.decompiler.languages.java.ast.AstBuilder.createTypeCore(AstBuilder.java:605)
        //     at com.strobel.decompiler.languages.java.ast.AstBuilder.createTypeNoCache(AstBuilder.java:195)
        //     at com.strobel.decompiler.languages.java.ast.AstBuilder.createType(AstBuilder.java:162)
        //     at com.strobel.decompiler.languages.java.ast.AstBuilder.addType(AstBuilder.java:137)
        //     at com.strobel.decompiler.languages.java.JavaLanguage.buildAst(JavaLanguage.java:71)
        //     at com.strobel.decompiler.languages.java.JavaLanguage.decompileType(JavaLanguage.java:59)
        //     at com.strobel.decompiler.DecompilerDriver.decompileType(DecompilerDriver.java:333)
        //     at com.strobel.decompiler.DecompilerDriver.decompileJar(DecompilerDriver.java:254)
        //     at com.strobel.decompiler.DecompilerDriver.main(DecompilerDriver.java:129)
        // 
        throw new IllegalStateException("An error occurred while decompiling this method.");
    }
    
    public final q7r<pr4> c(final boolean b, final m76 m76, final int n) {
        m76.x(264799724);
        final ea6$b a = ea6.a;
        long n2;
        if (b) {
            n2 = this.t;
        }
        else {
            n2 = this.u;
        }
        final q7r v = nkz.v((Object)new pr4(n2), m76);
        m76.O();
        return (q7r<pr4>)v;
    }
    
    public final q7r<pr4> d(final boolean b, final boolean b2, final cvd cvd, final m76 m76, final int n) {
        m76.x(998675979);
        final ea6$b a = ea6.a;
        final q7r a2 = bfb.a(cvd, m76, n >> 6 & 0xE);
        long n2;
        if (!b) {
            n2 = this.h;
        }
        else if (b2) {
            n2 = this.g;
        }
        else if (a2.getValue()) {
            n2 = this.e;
        }
        else {
            n2 = this.f;
        }
        q7r q7r;
        if (b) {
            m76.x(-2054190426);
            q7r = fcq.a(n2, (dc0)lr0.V(150, 0, (cq9)null, 6), m76, 48);
            m76.O();
        }
        else {
            m76.x(-2054190321);
            q7r = nkz.v((Object)new pr4(n2), m76);
            m76.O();
        }
        m76.O();
        return (q7r<pr4>)q7r;
    }
    
    public final q7r<pr4> e(final boolean b, final boolean b2, final cvd cvd, final m76 m76, final int n) {
        zzd.f((Object)cvd, "interactionSource");
        m76.x(727091888);
        final ea6$b a = ea6.a;
        final q7r a2 = bfb.a(cvd, m76, n >> 6 & 0xE);
        long n2;
        if (!b) {
            n2 = this.r;
        }
        else if (b2) {
            n2 = this.s;
        }
        else if (a2.getValue()) {
            n2 = this.p;
        }
        else {
            n2 = this.q;
        }
        final q7r v = nkz.v((Object)new pr4(n2), m76);
        m76.O();
        return (q7r<pr4>)v;
    }
    
    @Override
    public final boolean equals(final Object o) {
        if (this == o) {
            return true;
        }
        if (o != null && zzd.a((Object)g9m.a((Class)lk8.class), (Object)g9m.a((Class)o.getClass()))) {
            final lk8 lk8 = (lk8)o;
            return pr4.c(this.a, lk8.a) && pr4.c(this.b, lk8.b) && pr4.c(this.c, lk8.c) && pr4.c(this.d, lk8.d) && pr4.c(this.e, lk8.e) && pr4.c(this.f, lk8.f) && pr4.c(this.g, lk8.g) && pr4.c(this.h, lk8.h) && pr4.c(this.i, lk8.i) && pr4.c(this.j, lk8.j) && pr4.c(this.k, lk8.k) && pr4.c(this.l, lk8.l) && pr4.c(this.m, lk8.m) && pr4.c(this.n, lk8.n) && pr4.c(this.o, lk8.o) && pr4.c(this.p, lk8.p) && pr4.c(this.q, lk8.q) && pr4.c(this.r, lk8.r) && pr4.c(this.s, lk8.s) && pr4.c(this.t, lk8.t) && pr4.c(this.u, lk8.u);
        }
        return false;
    }
    
    public final q7r<pr4> f(final boolean b, final m76 m76, final int n) {
        m76.x(9804418);
        final ea6$b a = ea6.a;
        long n2;
        if (b) {
            n2 = this.a;
        }
        else {
            n2 = this.b;
        }
        final q7r v = nkz.v((Object)new pr4(n2), m76);
        m76.O();
        return (q7r<pr4>)v;
    }
    
    public final q7r<pr4> g(final boolean b, final m76 m76, final int n) {
        m76.x(-1446422485);
        final ea6$b a = ea6.a;
        long n2;
        if (b) {
            n2 = this.d;
        }
        else {
            n2 = this.c;
        }
        final q7r v = nkz.v((Object)new pr4(n2), m76);
        m76.O();
        return (q7r<pr4>)v;
    }
    
    public final q7r<pr4> h(final boolean b, final boolean b2, final m76 m76, final int n) {
        m76.x(1016171324);
        final ea6$b a = ea6.a;
        long n2;
        if (!b) {
            n2 = this.j;
        }
        else if (b2) {
            n2 = this.k;
        }
        else {
            n2 = this.i;
        }
        final q7r v = nkz.v((Object)new pr4(n2), m76);
        m76.O();
        return (q7r<pr4>)v;
    }
    
    @Override
    public final int hashCode() {
        return pr4.i(this.u) + xa0.d(this.t, xa0.d(this.s, xa0.d(this.r, xa0.d(this.q, xa0.d(this.p, xa0.d(this.o, xa0.d(this.n, xa0.d(this.m, xa0.d(this.l, xa0.d(this.k, xa0.d(this.j, xa0.d(this.i, xa0.d(this.h, xa0.d(this.g, xa0.d(this.f, xa0.d(this.e, xa0.d(this.d, xa0.d(this.c, xa0.d(this.b, pr4.i(this.a) * 31, 31), 31), 31), 31), 31), 31), 31), 31), 31), 31), 31), 31), 31), 31), 31), 31), 31), 31), 31);
    }
}
