import com.twitter.util.user.UserIdentifier;
import android.view.LayoutInflater;
import android.content.res.Resources;
import android.content.Intent;

// 
// Decompiled by Procyon v0.6.0
// 

public final class ulx extends kcv
{
    public ulx(final vlx p0, final int p1, final Intent p2, final k9x p3, final Resources p4, final cbs p5, final mxe<tai> p6, final nn p7, final dob p8, final cbf p9, final cbg p10, final LayoutInflater p11, final fda<h5h> p12, final UserIdentifier p13, final mcv p14, final mxe<ypa> p15, final a7g p16, final o9p p17, final ibm p18, final fci<?> p19, final c8p p20, final m9p p21) {
        // 
        // This method could not be decompiled.
        // 
        // Original Bytecode:
        // 
        //     1: aload_2        
        //     2: aload_3        
        //     3: aload           4
        //     5: aload           5
        //     7: aload           6
        //     9: aload           7
        //    11: aload           8
        //    13: aload           9
        //    15: aload           10
        //    17: aload           11
        //    19: aload           12
        //    21: aload           13
        //    23: aload           14
        //    25: aload           15
        //    27: aload           16
        //    29: aload           17
        //    31: aload           18
        //    33: aload           19
        //    35: aload           20
        //    37: aload           21
        //    39: invokespecial   kcv.<init>:(Landroid/content/Intent;Lk9x;Landroid/content/res/Resources;Lcbs;Lmxe;Lnn;Ldob;Lcbf;Lcbg;Landroid/view/LayoutInflater;Lfda;Lcom/twitter/util/user/UserIdentifier;Lmcv;Lmxe;La7g;Lo9p;Libm;Lfci;Lc8p;Lm9p;)V
        //    42: aload_0        
        //    43: aload_1        
        //    44: getfield        vlx.t:Lmkx;
        //    47: ldc             2131624013
        //    49: aconst_null    
        //    50: aconst_null    
        //    51: bipush          6
        //    53: invokestatic    mkx.c:(Lmkx;ILandroid/view/ViewGroup;Lstb;I)Leo6;
        //    56: checkcast       Lmkx$a;
        //    59: getfield        mkx$a.F0:Lvn6;
        //    62: invokeinterface vn6.getView:()Landroid/view/View;
        //    67: invokevirtual   u9.R4:(Landroid/view/View;)V
        //    70: return         
        //    Signature:
        //  (Lvlx;ILandroid/content/Intent;Lk9x;Landroid/content/res/Resources;Lcbs;Lmxe<Ltai;>;Lnn;Ldob;Lcbf;Lcbg;Landroid/view/LayoutInflater;Lfda<Lh5h;>;Lcom/twitter/util/user/UserIdentifier;Lmcv;Lmxe<Lypa;>;La7g;Lo9p;Libm;Lfci<*>;Lc8p;Lm9p;)V
        // 
        // The error that occurred was:
        // 
        // java.lang.ArrayIndexOutOfBoundsException: 22
        //     at com.strobel.decompiler.ast.AstBuilder.performStackAnalysis(AstBuilder.java:2030)
        //     at com.strobel.decompiler.ast.AstBuilder.build(AstBuilder.java:108)
        //     at com.strobel.decompiler.languages.java.ast.AstMethodBodyBuilder.createMethodBody(AstMethodBodyBuilder.java:203)
        //     at com.strobel.decompiler.languages.java.ast.AstMethodBodyBuilder.createMethodBody(AstMethodBodyBuilder.java:93)
        //     at com.strobel.decompiler.languages.java.ast.AstBuilder.createMethodBody(AstBuilder.java:868)
        //     at com.strobel.decompiler.languages.java.ast.AstBuilder.createConstructor(AstBuilder.java:799)
        //     at com.strobel.decompiler.languages.java.ast.AstBuilder.addTypeMembers(AstBuilder.java:635)
        //     at com.strobel.decompiler.languages.java.ast.AstBuilder.createTypeCore(AstBuilder.java:605)
        //     at com.strobel.decompiler.languages.java.ast.AstBuilder.createTypeNoCache(AstBuilder.java:195)
        //     at com.strobel.decompiler.languages.java.ast.AstBuilder.createType(AstBuilder.java:162)
        //     at com.strobel.decompiler.languages.java.ast.AstBuilder.addType(AstBuilder.java:137)
        //     at com.strobel.decompiler.languages.java.JavaLanguage.buildAst(JavaLanguage.java:71)
        //     at com.strobel.decompiler.languages.java.JavaLanguage.decompileType(JavaLanguage.java:59)
        //     at com.strobel.decompiler.DecompilerDriver.decompileType(DecompilerDriver.java:333)
        //     at com.strobel.decompiler.DecompilerDriver.decompileJar(DecompilerDriver.java:254)
        //     at com.strobel.decompiler.DecompilerDriver.main(DecompilerDriver.java:129)
        // 
        throw new IllegalStateException("An error occurred while decompiling this method.");
    }
}
