// 
// Decompiled by Procyon v0.6.0
// 

public final class zk8 implements lgs
{
    public final long a;
    public final long b;
    public final long c;
    public final long d;
    public final long e;
    public final long f;
    public final long g;
    public final long h;
    public final long i;
    public final long j;
    public final long k;
    public final long l;
    public final long m;
    public final long n;
    public final long o;
    public final long p;
    public final long q;
    public final long r;
    public final long s;
    public final long t;
    public final long u;
    
    public zk8(final long a, final long b, final long c, final long d, final long e, final long f, final long g, final long h, final long i, final long j, final long k, final long l, final long m, final long n, final long o, final long p21, final long q, final long r, final long s, final long t, final long u) {
        this.a = a;
        this.b = b;
        this.c = c;
        this.d = d;
        this.e = e;
        this.f = f;
        this.g = g;
        this.h = h;
        this.i = i;
        this.j = j;
        this.k = k;
        this.l = l;
        this.m = m;
        this.n = n;
        this.o = o;
        this.p = p21;
        this.q = q;
        this.r = r;
        this.s = s;
        this.t = t;
        this.u = u;
    }
    
    public final l9r<sr4> a(final boolean b, final boolean b2, final d86 d86, final int n) {
        d86.x(225259054);
        final sa6$b a = sa6.a;
        long n2;
        if (!b) {
            n2 = this.m;
        }
        else if (b2) {
            n2 = this.n;
        }
        else {
            n2 = this.l;
        }
        final l9r h0 = zzz.h0((Object)new sr4(n2), d86);
        d86.O();
        return (l9r<sr4>)h0;
    }
    
    public final l9r<sr4> b(final boolean p0, final d86 p1, final int p2) {
        // 
        // This method could not be decompiled.
        // 
        // Original Bytecode:
        // 
        //     1: ldc             -1423938813
        //     3: invokeinterface d86.x:(I)V
        //     8: getstatic       sa6.a:Lsa6$b;
        //    11: astore_2       
        //    12: new             Lsr4;
        //    15: dup            
        //    16: aload_0        
        //    17: getfield        zk8.o:J
        //    20: invokespecial   sr4.<init>:(J)V
        //    23: aload_1        
        //    24: invokestatic    zzz.h0:(Ljava/lang/Object;Ld86;)Ll9r;
        //    27: astore_2       
        //    28: aload_1        
        //    29: invokeinterface d86.O:()V
        //    34: aload_2        
        //    35: areturn        
        //    Signature:
        //  (ZLd86;I)Ll9r<Lsr4;>;
        // 
        // The error that occurred was:
        // 
        // java.lang.ArrayIndexOutOfBoundsException: 3
        //     at com.strobel.decompiler.ast.AstBuilder.performStackAnalysis(AstBuilder.java:2016)
        //     at com.strobel.decompiler.ast.AstBuilder.build(AstBuilder.java:108)
        //     at com.strobel.decompiler.languages.java.ast.AstMethodBodyBuilder.createMethodBody(AstMethodBodyBuilder.java:203)
        //     at com.strobel.decompiler.languages.java.ast.AstMethodBodyBuilder.createMethodBody(AstMethodBodyBuilder.java:93)
        //     at com.strobel.decompiler.languages.java.ast.AstBuilder.createMethodBody(AstBuilder.java:868)
        //     at com.strobel.decompiler.languages.java.ast.AstBuilder.createMethod(AstBuilder.java:761)
        //     at com.strobel.decompiler.languages.java.ast.AstBuilder.addTypeMembers(AstBuilder.java:638)
        //     at com.strobel.decompiler.languages.java.ast.AstBuilder.createTypeCore(AstBuilder.java:605)
        //     at com.strobel.decompiler.languages.java.ast.AstBuilder.createTypeNoCache(AstBuilder.java:195)
        //     at com.strobel.decompiler.languages.java.ast.AstBuilder.createType(AstBuilder.java:162)
        //     at com.strobel.decompiler.languages.java.ast.AstBuilder.addType(AstBuilder.java:137)
        //     at com.strobel.decompiler.languages.java.JavaLanguage.buildAst(JavaLanguage.java:71)
        //     at com.strobel.decompiler.languages.java.JavaLanguage.decompileType(JavaLanguage.java:59)
        //     at com.strobel.decompiler.DecompilerDriver.decompileType(DecompilerDriver.java:333)
        //     at com.strobel.decompiler.DecompilerDriver.decompileJar(DecompilerDriver.java:254)
        //     at com.strobel.decompiler.DecompilerDriver.main(DecompilerDriver.java:129)
        // 
        throw new IllegalStateException("An error occurred while decompiling this method.");
    }
    
    public final l9r<sr4> c(final boolean b, final d86 d86, final int n) {
        d86.x(264799724);
        final sa6$b a = sa6.a;
        long n2;
        if (b) {
            n2 = this.t;
        }
        else {
            n2 = this.u;
        }
        final l9r h0 = zzz.h0((Object)new sr4(n2), d86);
        d86.O();
        return (l9r<sr4>)h0;
    }
    
    public final l9r<sr4> d(final boolean b, final boolean b2, final hvd hvd, final d86 d86, final int n) {
        d86.x(998675979);
        final sa6$b a = sa6.a;
        final l9r a2 = afb.a(hvd, d86, n >> 6 & 0xE);
        long n2;
        if (!b) {
            n2 = this.h;
        }
        else if (b2) {
            n2 = this.g;
        }
        else if (a2.getValue()) {
            n2 = this.e;
        }
        else {
            n2 = this.f;
        }
        l9r l9r;
        if (b) {
            d86.x(-2054190426);
            l9r = tdq.a(n2, (ac0)eg8.M0(150, 0, null, 6), d86, 48);
            d86.O();
        }
        else {
            d86.x(-2054190321);
            l9r = zzz.h0((Object)new sr4(n2), d86);
            d86.O();
        }
        d86.O();
        return (l9r<sr4>)l9r;
    }
    
    public final l9r<sr4> e(final boolean b, final boolean b2, final hvd hvd, final d86 d86, final int n) {
        e0e.f((Object)hvd, "interactionSource");
        d86.x(727091888);
        final sa6$b a = sa6.a;
        final l9r a2 = afb.a(hvd, d86, n >> 6 & 0xE);
        long n2;
        if (!b) {
            n2 = this.r;
        }
        else if (b2) {
            n2 = this.s;
        }
        else if (a2.getValue()) {
            n2 = this.p;
        }
        else {
            n2 = this.q;
        }
        final l9r h0 = zzz.h0((Object)new sr4(n2), d86);
        d86.O();
        return (l9r<sr4>)h0;
    }
    
    @Override
    public final boolean equals(final Object o) {
        if (this == o) {
            return true;
        }
        if (o != null && e0e.a((Object)iam.a((Class)zk8.class), (Object)iam.a((Class)o.getClass()))) {
            final zk8 zk8 = (zk8)o;
            return sr4.c(this.a, zk8.a) && sr4.c(this.b, zk8.b) && sr4.c(this.c, zk8.c) && sr4.c(this.d, zk8.d) && sr4.c(this.e, zk8.e) && sr4.c(this.f, zk8.f) && sr4.c(this.g, zk8.g) && sr4.c(this.h, zk8.h) && sr4.c(this.i, zk8.i) && sr4.c(this.j, zk8.j) && sr4.c(this.k, zk8.k) && sr4.c(this.l, zk8.l) && sr4.c(this.m, zk8.m) && sr4.c(this.n, zk8.n) && sr4.c(this.o, zk8.o) && sr4.c(this.p, zk8.p) && sr4.c(this.q, zk8.q) && sr4.c(this.r, zk8.r) && sr4.c(this.s, zk8.s) && sr4.c(this.t, zk8.t) && sr4.c(this.u, zk8.u);
        }
        return false;
    }
    
    public final l9r<sr4> f(final boolean b, final d86 d86, final int n) {
        d86.x(9804418);
        final sa6$b a = sa6.a;
        long n2;
        if (b) {
            n2 = this.a;
        }
        else {
            n2 = this.b;
        }
        final l9r h0 = zzz.h0((Object)new sr4(n2), d86);
        d86.O();
        return (l9r<sr4>)h0;
    }
    
    public final l9r<sr4> g(final boolean b, final d86 d86, final int n) {
        d86.x(-1446422485);
        final sa6$b a = sa6.a;
        long n2;
        if (b) {
            n2 = this.d;
        }
        else {
            n2 = this.c;
        }
        final l9r h0 = zzz.h0((Object)new sr4(n2), d86);
        d86.O();
        return (l9r<sr4>)h0;
    }
    
    public final l9r<sr4> h(final boolean b, final boolean b2, final d86 d86, final int n) {
        d86.x(1016171324);
        final sa6$b a = sa6.a;
        long n2;
        if (!b) {
            n2 = this.j;
        }
        else if (b2) {
            n2 = this.k;
        }
        else {
            n2 = this.i;
        }
        final l9r h0 = zzz.h0((Object)new sr4(n2), d86);
        d86.O();
        return (l9r<sr4>)h0;
    }
    
    @Override
    public final int hashCode() {
        return sr4.i(this.u) + go0.h(this.t, go0.h(this.s, go0.h(this.r, go0.h(this.q, go0.h(this.p, go0.h(this.o, go0.h(this.n, go0.h(this.m, go0.h(this.l, go0.h(this.k, go0.h(this.j, go0.h(this.i, go0.h(this.h, go0.h(this.g, go0.h(this.f, go0.h(this.e, go0.h(this.d, go0.h(this.c, go0.h(this.b, sr4.i(this.a) * 31, 31), 31), 31), 31), 31), 31), 31), 31), 31), 31), 31), 31), 31), 31), 31), 31), 31), 31), 31);
    }
}
