import android.content.Context;

// 
// Decompiled by Procyon v0.6.0
// 

public final class zxh extends mts
{
    public zxh(final ybv p0, final aws p1, final qrs p2, final zh7<vo6> p3, final udf<nws> p4, final dsb p5, final rpd p6, final zoi<nws> p7, final Context p8, final uc p9, final exs p10, final g0t p11, final x3e<nws> p12, final pca<bo> p13, final adx p14, final jev p15, final f6j<pmi, t2g<i4e<Object>>> p16) {
        // 
        // This method could not be decompiled.
        // 
        // Original Bytecode:
        // 
        //     1: aload_1        
        //     2: aload_2        
        //     3: aload_3        
        //     4: aload           4
        //     6: aload           5
        //     8: aload           6
        //    10: aload           7
        //    12: aload           8
        //    14: aload           10
        //    16: aload           11
        //    18: aload           12
        //    20: aload           13
        //    22: aload           14
        //    24: aload           15
        //    26: aload           16
        //    28: invokespecial   mts.<init>:(Lybv;Laws;Lqrs;Lzh7;Ludf;Ldsb;Lrpd;Lzoi;Luc;Lexs;Lg0t;Lx3e;Lpca;Ladx;Ljev;)V
        //    31: return         
        //    Signature:
        //  (Lybv;Laws;Lqrs;Lzh7<Lvo6;>;Ludf<Lnws;>;Ldsb;Lrpd;Lzoi<Lnws;>;Landroid/content/Context;Luc;Lexs;Lg0t;Lx3e<Lnws;>;Lpca<Lbo;>;Ladx;Ljev;Lf6j<Lpmi;Lt2g<Li4e<Ljava/lang/Object;>;>;>;)V
        // 
        // The error that occurred was:
        // 
        // java.lang.ArrayIndexOutOfBoundsException: 17
        //     at com.strobel.decompiler.ast.AstBuilder.performStackAnalysis(AstBuilder.java:2030)
        //     at com.strobel.decompiler.ast.AstBuilder.build(AstBuilder.java:108)
        //     at com.strobel.decompiler.languages.java.ast.AstMethodBodyBuilder.createMethodBody(AstMethodBodyBuilder.java:203)
        //     at com.strobel.decompiler.languages.java.ast.AstMethodBodyBuilder.createMethodBody(AstMethodBodyBuilder.java:93)
        //     at com.strobel.decompiler.languages.java.ast.AstBuilder.createMethodBody(AstBuilder.java:868)
        //     at com.strobel.decompiler.languages.java.ast.AstBuilder.createConstructor(AstBuilder.java:799)
        //     at com.strobel.decompiler.languages.java.ast.AstBuilder.addTypeMembers(AstBuilder.java:635)
        //     at com.strobel.decompiler.languages.java.ast.AstBuilder.createTypeCore(AstBuilder.java:605)
        //     at com.strobel.decompiler.languages.java.ast.AstBuilder.createTypeNoCache(AstBuilder.java:195)
        //     at com.strobel.decompiler.languages.java.ast.AstBuilder.createType(AstBuilder.java:162)
        //     at com.strobel.decompiler.languages.java.ast.AstBuilder.addType(AstBuilder.java:137)
        //     at com.strobel.decompiler.languages.java.JavaLanguage.buildAst(JavaLanguage.java:71)
        //     at com.strobel.decompiler.languages.java.JavaLanguage.decompileType(JavaLanguage.java:59)
        //     at com.strobel.decompiler.DecompilerDriver.decompileType(DecompilerDriver.java:333)
        //     at com.strobel.decompiler.DecompilerDriver.decompileJar(DecompilerDriver.java:254)
        //     at com.strobel.decompiler.DecompilerDriver.main(DecompilerDriver.java:129)
        // 
        throw new IllegalStateException("An error occurred while decompiling this method.");
    }
    
    @Override
    public final lcv$b m0(final lcv$b lcv$b) {
        lcv$b.a = "mutual_following";
        return lcv$b;
    }
    
    @Override
    public final v4f o0() {
        return (v4f)new qf6((kyr)new yxh(this), true, (qf6$a)this);
    }
}
